{
  "has" : {
    "Approach" : {
      "investigate" : {
        "several methods" : {
          "of" : {
            "constructing" : {
              "an" : "auxiliary sentence"
            }
          }
        }
      },
      "transform" : {
        "( T ) ABSA" : {
          "into" : "sentence - pair classification task"
        },
        "from sentence" : "In this paper , we investigate several methods of constructing an auxiliary sentence and transform ( T ) ABSA into a sentence - pair classification task ."
      },
      "fine - tune" : {
        "pre-trained model" : {
          "from" : "BERT"
        },
        "from sentence" : "We fine - tune the pre-trained model from BERT and achieve new state - of - the - art results on ( T ) ABSA task ."
      }
    }
  }
}